system_shared_tool/__init__.py
system_shared_tool/context.py
system_shared_tool/sys_shd_channels.py
system_shared_tool/sys_shd_common.py
system_shared_tool/sys_shd_objects.py
system_shared_tool-0.2.14.dist-info/LICENSE.txt
system_shared_tool-0.2.14.dist-info/METADATA
system_shared_tool-0.2.14.dist-info/WHEEL
system_shared_tool-0.2.14.dist-info/top_level.txt
system_shared_tool-0.2.14.dist-info/RECORD
