Metadata-Version: 2.1
Name: system-shared-tool
Version: 0.2.14
Summary: Toolchain used for Inter Process Communication (IPC) on python platform.
Author-email: Marius Crisan <mariuscrsn+pypi@gmail.com>, Pablo Pastor <pastorpflores+pypi@gmail.com>, Javier Sanz <javiersanzmoline@gmail.com>, Roberto Aldea <r.aldea.csic+pypi@gmail.com>, Luis Roche <luis.roche@hotmail.com>
License: GNU GENERAL PUBLIC LICENSE
Project-URL: Homepage, https://github.com/WattRex/System-Tools
Project-URL: Bug Reports, https://github.com/WattRex/System-Tools/issues
Project-URL: Bug Tracker, https://github.com/WattRex/Battery-Cycler-Drivers/issues
Project-URL: Source, https://github.com/WattRex/System-Tools/code/sys_conf
Project-URL: Funding, https://donate.pypi.org
Keywords: yaml,configuration,synchronization,IPC,channel message,queue,multithreading,concurrency,parallel,messaging
Classifier: Development Status :: 3 - Alpha
Classifier: Topic :: Software Development :: Embedded Systems
Classifier: Operating System :: OS Independent
Classifier: License :: OSI Approved :: GNU Affero General Public License v3
Classifier: Programming Language :: Python :: 3
Classifier: Programming Language :: Python :: 3.7
Classifier: Programming Language :: Python :: 3.8
Classifier: Programming Language :: Python :: 3.9
Classifier: Programming Language :: Python :: 3.10
Classifier: Programming Language :: Python :: 3.11
Classifier: Programming Language :: Python :: 3 :: Only
Requires-Python: >=3.7
License-File: LICENSE.txt
Requires-Dist: posix-ipc >=1.1.1
Requires-Dist: PyYAML >=6.0.1
Requires-Dist: system-config-tool >=0.0.7
Requires-Dist: system-logger-tool >=0.2.2
